napari_macrokit/__init__.py
napari_macrokit/_literals.py
napari_macrokit/_macrokit_ext.py
napari_macrokit/_register_types.py
napari_macrokit/_rename.py
napari_macrokit/_type_resolution.py
napari_macrokit/core.py
napari_macrokit/napari.yaml
napari_macrokit/_tests/__init__.py
napari_macrokit/_tests/_utils.py
napari_macrokit/_tests/test_core.py
napari_macrokit/_tests/test_literal.py
napari_macrokit/_tests/test_macro_recording.py
napari_macrokit/_tests/test_recording_napari.py
napari_macrokit/_tests/test_returned_value.py
napari_macrokit/_tests/test_type_resolution.py
napari_macrokit/_tests/test_widgets.py
napari_macrokit/_widgets/__init__.py
napari_macrokit/_widgets/_code_editor.py
napari_macrokit/_widgets/_tab_widget.py
napari_macrokit-0.0.1.dist-info/LICENSE
napari_macrokit-0.0.1.dist-info/METADATA
napari_macrokit-0.0.1.dist-info/WHEEL
napari_macrokit-0.0.1.dist-info/entry_points.txt
napari_macrokit-0.0.1.dist-info/top_level.txt
napari_macrokit-0.0.1.dist-info/RECORD
