Metadata-Version: 2.1
Name: napari-macrokit
Version: 0.0.1
Summary: Executable script generation for napari plugins
Home-page: https://github.com/hanjinliu/napari-macrokit
Author: Hanjin Liu
Author-email: liuhanjin-sc@g.ecc.u-tokyo.ac.jp
License: BSD-3-Clause
Project-URL: Bug Tracker, https://github.com/hanjinliu/napari-macrokit/issues
Project-URL: Documentation, https://github.com/hanjinliu/napari-macrokit#README.md
Project-URL: Source Code, https://github.com/hanjinliu/napari-macrokit
Project-URL: User Support, https://github.com/hanjinliu/napari-macrokit/issues
Classifier: Development Status :: 2 - Pre-Alpha
Classifier: Framework :: napari
Classifier: Intended Audience :: Developers
Classifier: License :: OSI Approved :: BSD License
Classifier: Operating System :: OS Independent
Classifier: Programming Language :: Python
Classifier: Programming Language :: Python :: 3
Classifier: Programming Language :: Python :: 3 :: Only
Classifier: Programming Language :: Python :: 3.8
Classifier: Programming Language :: Python :: 3.9
Classifier: Programming Language :: Python :: 3.10
Classifier: Topic :: Scientific/Engineering :: Image Processing
Requires-Python: >=3.8
License-File: LICENSE
Requires-Dist: numpy
Requires-Dist: magicgui
Requires-Dist: qtpy
Requires-Dist: macro-kit (>=0.4.0)
Provides-Extra: testing
Requires-Dist: tox ; extra == 'testing'
Requires-Dist: pytest ; extra == 'testing'
Requires-Dist: pytest-cov ; extra == 'testing'
Requires-Dist: pytest-qt ; extra == 'testing'
Requires-Dist: napari ; extra == 'testing'
Requires-Dist: pyqt5 ; extra == 'testing'
